BiVFM/__init__.py
BiVFM/config_transfer.py
BiVFM/feature_engineering.py
BiVFM/func.py
BiVFM/model.py
BiVFM/olga_func.py
BiVFM/train_func.py
HVFM-1.0.0.dist-info/METADATA
HVFM-1.0.0.dist-info/WHEEL
HVFM-1.0.0.dist-info/top_level.txt
HVFM-1.0.0.dist-info/RECORD
