Metadata-Version: 2.1
Name: HVFM
Version: 1.0.0
Summary: Paper: Hybrid Virtual Flow Metering on Arbitrary Well Patterns for Transient Multiphase Prediction Driven by Mechanistic and Data Model
Home-page: https://pypi.org/project/BiVFM-Fleet
Author: He Ma
Author-email: mahepetroleum@163.com
License: UNKNOWN
Keywords: Virtual flow meter,neural network
Platform: UNKNOWN
Classifier: Programming Language :: Python :: 3
Classifier: License :: OSI Approved :: MIT License
Classifier: Operating System :: OS Independent
